segT/__init__.py
segT/myfunctions.py
segT-0.1.0.dist-info/METADATA
segT-0.1.0.dist-info/WHEEL
segT-0.1.0.dist-info/top_level.txt
segT-0.1.0.dist-info/RECORD
